DPSOP/__init__.py
DPSOP/classify.py
DPSOP-0.0.6.dist-info/LICENSE
DPSOP-0.0.6.dist-info/METADATA
DPSOP-0.0.6.dist-info/WHEEL
DPSOP-0.0.6.dist-info/top_level.txt
DPSOP-0.0.6.dist-info/RECORD
