Metadata-Version: 2.1
Name: DPSOP
Version: 0.0.6
Summary: 深度学习 模型训练的流程库
Home-page: https://github.com/buffaloboyhlh/DPSOP
Author: buffalohlh
Author-email: buffaloboyhu@gmail.com
License: MIT
Classifier: Programming Language :: Python :: 3
Classifier: License :: OSI Approved :: MIT License
Classifier: Operating System :: OS Independent
Requires-Python: >=3.12
License-File: LICENSE
Requires-Dist: torch>=2.5.1
